{
  "id": "component-framework/store",
  "title": "Store — Reactive Shared State",
  "description": "Store wraps a value of type T behind Arc> with a listener list. Any number of components can share a clone of the same store. When the value is mutated, all subscribers are notified.",
  "source": "@site/docs/component-framework/store.md",
  "sourceDirName": "component-framework",
  "slug": "/component-framework/store",
  "permalink": "/docs/component-framework/store",
  "draft": false,
  "unlisted": false,
  "editUrl": "https://github.com/wgpu-html/wgpu-html/tree/master/www/docs/component-framework/store.md",
  "tags": [],
  "version": "current",
  "lastUpdatedAt": null,
  "frontMatter": {
    "title": "Store — Reactive Shared State"
  },
  "sidebar": "docs",
  "previous": {
    "title": "Ctx Callback Factory",
    "permalink": "/docs/component-framework/ctx"
  },
  "next": {
    "title": "Component Rendering Model",
    "permalink": "/docs/component-framework/rendering"
  }
}